README.rst
sense.py
setup.py
sense.egg-info/PKG-INFO
sense.egg-info/SOURCES.txt
sense.egg-info/dependency_links.txt
sense.egg-info/top_level.txt