Metadata-Version: 1.0
Name: sense
Version: 0.1.1
Summary: Standard Sense utilities for Python
Home-page: https://www.senseplatform.com
Author: Sense Inc.
Author-email: support@senseplatform.com
License: MIT
Platform: Sense
